[
  { "value": "AA", "label": "AA - Academic Affairs" },
  { "value": "AAA", "label": "AAA - Asian/Asian American Studies" },
  { "value": "ACC", "label": "ACC - Accountancy" },
  { "value": "ACE", "label": "ACE - American Culture and English Prg" },
  { "value": "AER", "label": "AER - Aeronautics" },
  { "value": "AES", "label": "AES - Aerospace Studies" },
  { "value": "AMS", "label": "AMS - American Studies" },
  { "value": "APC", "label": "APC - Applied Communication" },
  { "value": "ARB", "label": "ARB - Arabic" },
  { "value": "ARC", "label": "ARC - Architecture and Interior Design" },
  { "value": "ART", "label": "ART - Art" },
  { "value": "ASO", "label": "ASO - Applied Social Science" },
  { "value": "ATH", "label": "ATH - Anthropology" },
  { "value": "BIO", "label": "BIO - Biology" },
  { "value": "BIS", "label": "BIS - Integrative Studies" },
  { "value": "BLS", "label": "BLS - Business Legal Studies" },
  { "value": "BSC", "label": "BSC - Biological Sciences" },
  { "value": "BUS", "label": "BUS - Business Analysis" },
  { "value": "BWS", "label": "BWS - Black World Studies" },
  { "value": "CAS", "label": "CAS - College of Arts and Science" },
  { "value": "CCA", "label": "CCA - College of Creative Arts" },
  { "value": "CEC", "label": "CEC - Col of Engineering and Computing" },
  { "value": "CHI", "label": "CHI - Chinese" },
  { "value": "CHM", "label": "CHM - Chemistry and Biochemistry" },
  { "value": "CIT", "label": "CIT - Comp and Information Technology" },
  { "value": "CJS", "label": "CJS - Criminal Justice Studies" },
  { "value": "CLA", "label": "CLA - Col Liberal Arts and Applied Sci" },
  { "value": "CLS", "label": "CLS - Classics" },
  { "value": "CMA", "label": "CMA - Community Arts" },
  { "value": "CMR", "label": "CMR - Commerce" },
  { "value": "CMS", "label": "CMS - Comparative Media Studies" },
  { "value": "CPB", "label": "CPB - Chem, Paper and Biomed Engineer" },
  { "value": "CRD", "label": "CRD - Civic and Regional Development" },
  { "value": "CRE", "label": "CRE - Critical Race and Ethnic Studies" },
  { "value": "CSE", "label": "CSE - Comp Sci and Software Engineering" },
  { "value": "CYB", "label": "CYB - Cybersecurity" },
  { "value": "DST", "label": "DST - Disability Studies" },
  { "value": "ECE", "label": "ECE - Electrical and Computer Engineer" },
  { "value": "ECO", "label": "ECO - Economics" },
  { "value": "EDL", "label": "EDL - Educational Leadership" },
  { "value": "EDP", "label": "EDP - Educational Psychology" },
  { "value": "EDT", "label": "EDT - Teaching, Curriculum and Ed Inquiry" },
  { "value": "EGM", "label": "EGM - Engineering Management" },
  { "value": "EGS", "label": "EGS - English Studies" },
  { "value": "EHS", "label": "EHS - Education, Health and Society" },
  { "value": "ENG", "label": "ENG - English" },
  { "value": "ENT", "label": "ENT - Engineering Technology" },
  { "value": "ENV", "label": "ENV - Environmental Science" },
  { "value": "ESP", "label": "ESP - Entrepreneurship" },
  { "value": "FAS", "label": "FAS - Fashion" },
  { "value": "FIN", "label": "FIN - Finance" },
  { "value": "FRE", "label": "FRE - French" },
  { "value": "FST", "label": "FST - Film Studies" },
  { "value": "FSW", "label": "FSW - Family Science and Social Work" },
  { "value": "GEO", "label": "GEO - Geography" },
  { "value": "GER", "label": "GER - German" },
  { "value": "GHS", "label": "GHS - Global Health Studies" },
  { "value": "GIC", "label": "GIC - Global and Intercultural Studies" },
  { "value": "GLG", "label": "GLG - Geology" },
  { "value": "GRK", "label": "GRK - Greek Language and Literature" },
  { "value": "GSC", "label": "GSC - Graduate School Community" },
  { "value": "GTY", "label": "GTY - Gerontology" },
  { "value": "HON", "label": "HON - Honors" },
  { "value": "HST", "label": "HST - History" },
  { "value": "HUM", "label": "HUM - Humanities Center" },
  { "value": "IDS", "label": "IDS - Interdisciplinary" },
  { "value": "IES", "label": "IES - Environmental Sciences" },
  { "value": "IMS", "label": "IMS - Emerging Tech: BusinessandDesign" },
  { "value": "ISA", "label": "ISA - Information Systemsand Analytics" },
  { "value": "ITL", "label": "ITL - Italian" },
  { "value": "ITS", "label": "ITS - International Studies" },
  { "value": "JPN", "label": "JPN - Japanese" },
  { "value": "JRN", "label": "JRN - Journalism" },
  { "value": "KNH", "label": "KNH - Kinesiology,Nutrition and Health" },
  { "value": "KOR", "label": "KOR - Korean" },
  { "value": "LAS", "label": "LAS - Latin American Studies" },
  { "value": "LAT", "label": "LAT - Latin Language and Literature" },
  { "value": "LIN", "label": "LIN - Linguistics" },
  { "value": "LR", "label": "LR - Inst Learning in Retirement" },
  { "value": "LST", "label": "LST - Liberal Studies" },
  { "value": "LUX", "label": "LUX - Luxembourg" },
  { "value": "MAC", "label": "MAC - Media and Communication" },
  { "value": "MBI", "label": "MBI - Microbiology" },
  { "value": "MGT", "label": "MGT - Management" },
  { "value": "MJF", "label": "MJF - Media, Journalism and Film" },
  { "value": "MKT", "label": "MKT - Marketing" },
  { "value": "MME", "label": "MME - Mechan and Manufact Engineering" },
  { "value": "MMS", "label": "MMS - Medical Science" },
  { "value": "MSC", "label": "MSC - Military Science" },
  { "value": "MTH", "label": "MTH - Mathematics" },
  { "value": "MUS", "label": "MUS - Music" },
  { "value": "NCS", "label": "NCS - Nonprofit and Community Studies" },
  { "value": "NSC", "label": "NSC - Naval Science" },
  { "value": "NSG", "label": "NSG - Nursing" },
  { "value": "ORG", "label": "ORG - Organizational Leadership" },
  { "value": "PAS", "label": "PAS - Physician Associate Studies" },
  { "value": "PHL", "label": "PHL - Philosophy" },
  { "value": "PHY", "label": "PHY - Physics" },
  { "value": "PLW", "label": "PLW - Pre-Law Studies" },
  { "value": "PMD", "label": "PMD - Premedical Studies" },
  { "value": "POL", "label": "POL - Political Science" },
  { "value": "POR", "label": "POR - Portuguese" },
  { "value": "PSS", "label": "PSS - Psychological Science" },
  { "value": "PSY", "label": "PSY - Psychology" },
  { "value": "REL", "label": "REL - Religion, Comparative" },
  { "value": "RUS", "label": "RUS - Russian" },
  { "value": "SJS", "label": "SJS - Social Justice Studies" },
  { "value": "SLM", "label": "SLM - Sport Leadership and Management" },
  { "value": "SOC", "label": "SOC - Sociology" },
  { "value": "SPA", "label": "SPA - Speech Pathology and Audiology" },
  { "value": "SPN", "label": "SPN - Spanish" },
  { "value": "STA", "label": "STA - Statistics" },
  { "value": "STC", "label": "STC - Strategic Communication" },
  { "value": "TCE", "label": "TCE - Teaching,CurriculumandEd Inquiry" },
  { "value": "THE", "label": "THE - Theatre" },
  { "value": "UNV", "label": "UNV - University" },
  { "value": "WGS", "label": "WGS - Women,GenderandSexuality Studies" },
  { "value": "WST", "label": "WST - Western Program" }
]
